openvpn_control/__init__.py
openvpn_control/settings.py
openvpn_control/vpn.py
openvpn_control/utils/__init__.py
openvpn_control/utils/fileio.py
openvpn_control/utils/metadata.py
openvpn_control/utils/openvpn.py
python_openvpn_control-0.1.3.dist-info/LICENSE
python_openvpn_control-0.1.3.dist-info/METADATA
python_openvpn_control-0.1.3.dist-info/WHEEL
python_openvpn_control-0.1.3.dist-info/top_level.txt
python_openvpn_control-0.1.3.dist-info/RECORD
